Workbook

Sheet 前提条件
A1: 岩手県 10tダンプ（運転手付）1日原価 試算 ― 前提条件
A2: 凡例: 青字＝入力値（変更可）／黄色塗り＝結果への影響が大きい主要仮定／黒字＝計算式／緑字＝他シート参照。金額は税抜（円）。
A3: 作成日 2026-10-29。公式資料の値と『仮定』を区別して出典欄に記載。仮定は自社実績に置き換えて使用してください。
A4: 項目 | B4: 値 | C4: 単位 | D4: 区分 | E4: 出典・根拠
A5: ■ 共通
A6: 年間稼働日数 | B6: 250 | C6: 日/年 | D6: 仮定 | E6: 週5日×50週程度。自社実績で置換
A7: 軽油単価（税込・店頭） | B7: 154.9 | C7: 円/L | D7: 公表値 | E7: 資源エネルギー庁 石油製品価格調査 岩手県 2026/10週次（oil-stat.com / gasonavi 経由）。大口契約は数円〜十数円安いことが多い
A8: 消費税率 | B8: 0.1 | D8: 制度
A9: 軽油単価（税抜） | B9: =B7/(1+B8) -> 140.81818 | C9: 円/L | D9: 計算
A10: ■ 方式A：運送事業者の原価（標準的運賃の原価項目に準拠）
A11: 車両取得価格（架装込・税抜） | B11: 20000000 | C11: 円 | D11: 仮定 | E11: 新車10tダンプの販売相場 税込約1,800万〜2,500万円（中心2,000万円前後：トラック流通センター、GROOWAVE、SIGMA、販売店の2026年式実例2,491万円）を踏まえ2,000万円と設定。参考：新潟県 機械損料一覧表(R7.10適用)の積算用基礎価格は14,400千円
A12: 償却年数 | B12: 5 | C12: 年 | D12: 基準 | E12: 国交省『標準的な運賃』原価算定方法：償却年数5年
A13: 残存価額 | B13: 1 | C13: 円 | D13: 基準 | E13: 同上：残存価額は備忘価額1円
A14: 運転手 年間給与（賞与・手当込） | B14: 4000000 | C14: 円/年 | D14: 仮定 | E14: 岩手の大型ダンプ求人 日給8,000〜13,000円、月給19〜24万円＋賞与・残業を想定。自社実績で置換
A15: 法定福利費率（事業主負担） | B15: 0.16 | D15: 仮定 | E15: 健保・厚年・雇用・労災・子ども子育て拠出金の事業主負担の概算
A16: 自動車関係税（自動車税・重量税 年額） | B16: 90000 | C16: 円/年 | D16: 仮定 | E16: 営業用（緑ナンバー）10t車の概算。車検証の車両総重量で要確認
A17: 保険料（自賠責＋任意 年額） | B17: 400000 | C17: 円/年 | D17: 仮定 | E17: 対人対物無制限・車両保険なし程度の概算
A18: 車検・整備・修理費（年額） | B18: 500000 | C18: 円/年 | D18: 仮定
A19: タイヤ費（年額） | B19: 300000 | C19: 円/年 | D19: 仮定 | E19: 10本×約6万円を2年で交換程度
A20: オイル・尿素水・雑費（年額） | B20: 100000 | C20: 円/年 | D20: 仮定
A21: 1日あたり燃料消費量 | B21: 50 | C21: L/日 | D21: 仮定 | E21: 標準的運賃の基礎走行130km÷燃費約3.5km/L≒37L と 積算基準の運転日当り約58L の中間
A22: 一般管理費率（車庫・事務・通信等） | B22: 0.1 | D22: 仮定 | E22: 標準的運賃の『間接費』相当
A23: 適正利潤率 | B23: 0.05 | D23: 仮定
A24: ■ 方式B：公共工事積算（土木工事標準積算基準の『ダンプトラック運転 運転1日当り』構成）
A25: 運転手（一般）労務単価 岩手県 | B25: 26900 | C25: 円/人日 | D25: 公表値 | E25: 公共工事設計労務単価 令和8年3月適用（農水省・国交省）岩手県 運転手（一般）。法定福利費の事業主負担は含まない
A26: 運転日1日あたり運転時間 | B26: 5.9 | C26: h/日 | D26: 公表値 | E26: 新潟県 機械損料一覧表 10t積級（豪雪補正後）：年間運転830h÷運転日数140日。岩手(B地区)も同条件
A27: 機関出力 | B27: 246 | C27: kW | D27: 公表値 | E27: 同上 10t積級
A28: 燃料消費率 | B28: 0.04 | C28: L/kW·h | D28: 公表値 | E28: 同上（運転1時間当り燃料 9.8L）
A29: 供用1日当り換算損料（タイヤ損耗・補修費込） | B29: 22147 | C29: 円/供用日 | D29: 公表値 | E29: 新潟県農地部 機械損料一覧表(R7.10.20適用) MNS0301005（豪雪補正込・タイヤ損耗費及び補修費(良好)含む）。岩手県は独自の損料表を公表せず国交省『建設機械等損料表』を適用し、県内全市が豪雪B地区（県積算基準 運用編 R8.10）→豪雪補正込の本値と同じ扱い。令和8年度版の値は市販本（日本建設機械施工協会、11,000円）で確認し置換
A30: 年間供用日数 | B30: 180 | C30: 日 | D30: 公表値 | E30: 同上
A31: 年間運転日数 | B31: 140 | C31: 日 | D31: 公表値 | E31: 同上
A32: 諸経費率（現場管理費＋一般管理費 相当） | B32: 0.2 | D32: 仮定 | E32: 法定福利費・会社経費・利益を簡易に一括計上する率
A33: ■ 比較用：国交省『標準的な運賃』（令和6年3月告示）
A34: 東北 大型車(10t) 8時間制 基礎額 | B34: 52610 | C34: 円 | D34: 公表値 | E34: 全日本トラック協会『標準的運賃が改定されました』時間制運賃表（基礎走行130km・作業8時間以内）
A35: ダンプ車 特殊車両割増率 | B35: 0.2 | D35: 公表値 | E35: 同上【特殊車両割増】ダンプ車：大型車の2割
A36: 超過1時間あたり加算額（東北・大型） | B36: 3130 | C36: 円/h | D36: 公表値 | E36: 同上
A37: 超過10kmあたり加算額（東北・大型） | B37: 630 | C37: 円/10km | D37: 公表値 | E37: 同上

Sheet A_事業者原価
A1: 方式A：運送事業者の原価から見た 10tダンプ（運転手付）1日あたり原価
A2: 国交省『標準的な運賃』の原価項目（固定費・変動費・間接費・利潤）に沿って年間費用を積み上げ、稼働日数で割る。
A4: 区分 | B4: 費目 | C4: 年額（円） | D4: 1日あたり（円） | E4: 構成比 | F4: 計算式・備考
A5: 固定費 | B5: 車両償却費 | C5: =(前提条件!$B$11-前提条件!$B$13)/前提条件!$B$12 -> 3999999.8 | D5: =C5/前提条件!$B$6 -> 15999.999 | E5: =D5/$D$17 -> 0.29373508 | F5: (取得価格−残存価額)÷償却年数
A6: 固定費 | B6: 運転手 人件費（給与） | C6: =前提条件!$B$14 -> 4000000 | D6: =C6/前提条件!$B$6 -> 16000 | E6: =D6/$D$17 -> 0.29373509 | F6: 年間給与
A7: 固定費 | B7: 法定福利費（事業主負担） | C7: =前提条件!$B$14*前提条件!$B$15 -> 640000 | D7: =C7/前提条件!$B$6 -> 2560 | E7: =D7/$D$17 -> 0.046997615 | F7: 給与×法定福利費率
A8: 固定費 | B8: 自動車関係税 | C8: =前提条件!$B$16 -> 90000 | D8: =C8/前提条件!$B$6 -> 360 | E8: =D8/$D$17 -> 0.0066090396
A9: 固定費 | B9: 保険料 | C9: =前提条件!$B$17 -> 400000 | D9: =C9/前提条件!$B$6 -> 1600 | E9: =D9/$D$17 -> 0.029373509
A10: 準変動費 | B10: 車検・整備・修理費 | C10: =前提条件!$B$18 -> 500000 | D10: =C10/前提条件!$B$6 -> 2000 | E10: =D10/$D$17 -> 0.036716887
A11: 準変動費 | B11: タイヤ費 | C11: =前提条件!$B$19 -> 300000 | D11: =C11/前提条件!$B$6 -> 1200 | E11: =D11/$D$17 -> 0.022030132
A12: 準変動費 | B12: オイル・尿素水・雑費 | C12: =前提条件!$B$20 -> 100000 | D12: =C12/前提条件!$B$6 -> 400 | E12: =D12/$D$17 -> 0.0073433774
A13: 変動費 | B13: 燃料費 | C13: =前提条件!$B$21*前提条件!$B$9*前提条件!$B$6 -> 1760227.3 | D13: =C13/前提条件!$B$6 -> 7040.9091 | E13: =D13/$D$17 -> 0.12926013 | F13: 燃料L/日×軽油税抜単価×稼働日数
B14: 運送原価 小計 | C14: =SUM(C5:C13) -> 11790227 | D14: =SUM(D5:D13) -> 47160.908 | E14: =D14/$D$17 -> 0.86580087
A15: 間接費 | B15: 一般管理費 | C15: =C14*前提条件!$B$22 -> 1179022.7 | D15: =D14*前提条件!$B$22 -> 4716.0908 | E15: =D15/$D$17 -> 0.086580087 | F15: 小計×一般管理費率
A16: 利潤 | B16: 適正利潤 | C16: =(C14+C15)*前提条件!$B$23 -> 648462.49 | D16: =(D14+D15)*前提条件!$B$23 -> 2593.85 | E16: =D16/$D$17 -> 0.047619048 | F16: (小計＋一般管理費)×利潤率
B17: 合計（税抜）＝1日あたり適正料金の目安 | C17: =C14+C15+C16 -> 13617712 | D17: =D14+D15+D16 -> 54470.849 | E17: =D17/$D$17 -> 1
B18: 参考：税込 | D18: =D17*(1+前提条件!$B$8) -> 59917.934
A20: 注記
A21: ・稼働日数・車両価格・給与が結果を大きく左右する（『比較・感度』シート参照）。償却が終わった車両なら1日あたり約1.8万円下がる。車両価格100万円ごとに1日約920円変動。
A22: ・高速代、残土処分費、積込機械、時間外（8時間超）、深夜・休日割増は含まない。
A23: ・運転手付きで他者の荷物を有償運搬するには一般貨物自動車運送事業（緑ナンバー）の許可が必要。

Sheet B_公共積算
A1: 方式B：公共工事積算の構成で見た 10tダンプ（運転手付）運転1日あたり単価
A2: 土木工事標準積算基準『ダンプトラック運転（10t積級）運転1日当り単価表』の構成：運転手（一般）＋燃料（軽油）＋機械損料（タイヤ損耗費込）。
A4: 名称 | B4: 数量 | C4: 単位 | D4: 単価（円） | E4: 金額（円） | F4: 構成比 | G4: 備考
A5: 運転手（一般） | B5: =1 -> 1 | C5: 人 | D5: =前提条件!$B$25 -> 26900 | E5: =B5*D5 -> 26900 | F5: =E5/$E$10 -> 0.35274032 | G5: 岩手県 令和8年3月適用 労務単価
A6: 軽油 | B6: =前提条件!$B$27*前提条件!$B$28*前提条件!$B$26 -> 58.056 | C6: L | D6: =前提条件!$B$9 -> 140.81818 | E6: =B6*D6 -> 8175.3404 | F6: =E6/$E$10 -> 0.10720343 | G6: 出力×消費率×運転時間（≒58L）
A7: ダンプトラック損料（タイヤ損耗費込） | B7: =前提条件!$B$30/前提条件!$B$31 -> 1.2857143 | C7: 供用日 | D7: =前提条件!$B$29 -> 22147 | E7: =B7*D7 -> 28474.714 | F7: =E7/$E$10 -> 0.37338959 | G7: 運転1日あたり供用日数＝供用日数÷運転日数
A8: 直接費 小計 | E8: =SUM(E5:E7) -> 63550.055 | F8: =E8/$E$10 -> 0.83333333
A9: 諸経費（法定福利費・会社経費・利益 相当） | E9: =E8*前提条件!$B$32 -> 12710.011 | F9: =E9/$E$10 -> 0.16666667 | G9: 直接費×諸経費率（簡易）
A10: 合計（税抜） | E10: =E8+E9 -> 76260.066 | F10: =E10/$E$10 -> 1
A11: 参考：税込 | E11: =E10*(1+前提条件!$B$8) -> 83886.072
A13: 注記
A14: ・公共積算の損料は年間運転140日・供用180日を前提とするため、民間で年250日前後稼働する車両より1日あたりの車両費が高く出る。
A15: ・岩手県は損料表を独自公表しておらず、国交省『建設機械等損料表』を準用（県内全市は豪雪B地区）。本表は同じ国交省表に豪雪補正をかけて公表している新潟県（R7.10適用）の値を使用。令和8年度版の数値は市販本で確認して前提条件シートを置換すること。
A16: ・労務単価は賃金のみで、法定福利費の事業主負担は含まない（ここでは諸経費率に含めて計上）。

Sheet 比較・感度
A1: 比較と感度分析（税抜・円/日）
A3: 指標 | B3: 1日あたり（円） | C3: 備考
A4: 方式A：事業者原価（新車償却中） | B4: =A_事業者原価!$D$17 -> 54470.849 | C4: A_事業者原価シート
A5: 方式B：公共積算構成 | B5: =B_公共積算!$E$10 -> 76260.066 | C5: B_公共積算シート
A6: 標準的運賃 東北 大型ダンプ 8時間制 | B6: =前提条件!$B$34*(1+前提条件!$B$35) -> 63132 | C6: 基礎額×(1＋ダンプ割増2割)。燃料サーチャージ・高速代別
A7: 民間実勢（全国の料金表例）下限 | B7: 36000 | C7: 芝田建設 料金表 8時間
A8: 民間実勢（全国の料金表例）上限 | B8: 50000 | C8: 松田興業 料金表
A10: 感度分析：方式Aの1日原価 ― 年間稼働日数 × 車両の償却状況
A11: 年間稼働日数 | B11: 新車（償却中） | C11: 償却済み車両 | D11: 差額
A12: 150 | B12: =(SUM(A_事業者原価!$C$5:$C$12)/A12+(前提条件!$B$21*前提条件!$B$9))*(1+前提条件!$B$22)*(1+前提条件!$B$23) -> 85363.248 | C12: =((SUM(A_事業者原価!$C$5:$C$12)-A_事業者原価!$C$5)/A12+(前提条件!$B$21*前提条件!$B$9))*(1+前提条件!$B$22)*(1+前提条件!$B$23) -> 54563.25 | D12: =B12-C12 -> 30799.998
A13: 200 | B13: =(SUM(A_事業者原価!$C$5:$C$12)/A13+(前提条件!$B$21*前提条件!$B$9))*(1+前提条件!$B$22)*(1+前提条件!$B$23) -> 66055.499 | C13: =((SUM(A_事業者原価!$C$5:$C$12)-A_事業者原価!$C$5)/A13+(前提条件!$B$21*前提条件!$B$9))*(1+前提条件!$B$22)*(1+前提条件!$B$23) -> 42955.5 | D13: =B13-C13 -> 23099.999
A14: 225 | B14: =(SUM(A_事業者原価!$C$5:$C$12)/A14+(前提条件!$B$21*前提条件!$B$9))*(1+前提条件!$B$22)*(1+前提条件!$B$23) -> 59619.582 | C14: =((SUM(A_事業者原価!$C$5:$C$12)-A_事業者原価!$C$5)/A14+(前提条件!$B$21*前提条件!$B$9))*(1+前提条件!$B$22)*(1+前提条件!$B$23) -> 39086.25 | D14: =B14-C14 -> 20533.332
A15: 250 | B15: =(SUM(A_事業者原価!$C$5:$C$12)/A15+(前提条件!$B$21*前提条件!$B$9))*(1+前提条件!$B$22)*(1+前提条件!$B$23) -> 54470.849 | C15: =((SUM(A_事業者原価!$C$5:$C$12)-A_事業者原価!$C$5)/A15+(前提条件!$B$21*前提条件!$B$9))*(1+前提条件!$B$22)*(1+前提条件!$B$23) -> 35990.85 | D15: =B15-C15 -> 18479.999
A16: 275 | B16: =(SUM(A_事業者原価!$C$5:$C$12)/A16+(前提条件!$B$21*前提条件!$B$9))*(1+前提条件!$B$22)*(1+前提条件!$B$23) -> 50258.249 | C16: =((SUM(A_事業者原価!$C$5:$C$12)-A_事業者原価!$C$5)/A16+(前提条件!$B$21*前提条件!$B$9))*(1+前提条件!$B$22)*(1+前提条件!$B$23) -> 33458.25 | D16: =B16-C16 -> 16799.999
A18: 読み方
A19: ・方式A（新車2,000万円・年250日）は約5.4万円で民間実勢の上限（5万円）をやや上回る。償却済み車両なら約3.6万円で、実勢4万円前後の業者はこの水準と考えられる。
A20: ・方式Bは公共工事の年140日運転前提のため車両費が厚く、民間の傭車相場より高めに出る。
A21: ・標準的運賃（約6.3万円）は国が示す『適正原価＋適正利潤』の目安で、実取引はこれを下回ることが多い。値上げ交渉時の根拠として使える。
A22: ・8時間・130km超、待機、高速代、残土処分費、積込機械は別途精算が一般的。

Sheet 出典
A1: 出典一覧
A3: 国交省『標準的な運賃』の考え方・原価算定方法 | B3: https://www.mlit.go.jp/common/001358610.pdf
A4: 全日本トラック協会『標準的運賃が改定されました』（令和6年3月） | B4: https://jta.or.jp/wp-content/themes/jta_theme/pdf/202410unchin.pdf
A5: 令和8年3月から適用する公共工事設計労務単価表（農水省・国交省） | B5: https://www.rinya.maff.go.jp/j/sekou/gijutu/attach/pdf/sekisan_kijun-374.pdf
A6: 新潟県農地部 機械損料一覧表（令和7年10月20日以降適用・12月2日訂正版） | B6: https://www.pref.niigata.lg.jp/uploaded/attachment/474671.pdf
A7: 岩手県 令和8年度土木工事標準積算基準書（公表用）※損料表は国交省版を適用 | B7: https://www.pref.iwate.jp/kendozukuri/kensetsu/1093671/1101385.html
A8: 岩手県 土木工事標準積算基準書（運用編）令和8年10月1日以降適用 ※機械所在地の豪雪地域区分（岩手県全市＝B地区） | B8: https://www.pref.iwate.jp/_res/projects/default_project/_page_/001/101/385/261001_unnyouhen.pdf
A9: 日本建設機械施工協会『建設機械等損料表 令和8年度版』（市販） | B9: https://www.gov-book.or.jp/book/detail.php?product_id=408304
A10: 林野庁東北森林管理局 岩手南部 単価資料（10tダンプ内訳） | B10: https://www.rinya.maff.go.jp/tohoku/apply/publicsale/iwatenanbu/attach/pdf/tya-ta-2-5.pdf
A11: 岩手県の軽油価格（資源エネルギー庁調査ベース） | B11: https://oil-stat.com/light/%E5%B2%A9%E6%89%8B%E7%9C%8C.html
A12: トラック流通センター 大型ダンプの価格 | B12: https://www.kaitoriou.net/page/knowledge/type/11679/
A13: GROOWAVE 10tダンプの価格相場 | B13: https://groowave.com/blog/truck/10t-dump/
A14: SIGMA 10tダンプトラック解説 | B14: https://satei.sigmaintl.jp/column/10532
... A17: 求人ボックス 岩手県ダンプ運転手（給与水準の参考） | B17: https://xn--pckua2a7gp15o89zb.com/%E3%83%80%E3%83%B3%E3%83%97%E9%81%8B%E8%BB%A2%E6%89%8B%E3%81%AE%E4%BB%95%E4%BA%8B-%E5%B2%A9%E6%89%8B%E7%9C%8C
